bioblend/__init__.py
bioblend/config.py
bioblend/galaxyclient.py
bioblend/py.typed
bioblend/_tests/GalaxyTestBase.py
bioblend/_tests/TestGalaxyConfig.py
bioblend/_tests/TestGalaxyDatasetCollections.py
bioblend/_tests/TestGalaxyDatasets.py
bioblend/_tests/TestGalaxyFolders.py
bioblend/_tests/TestGalaxyGroups.py
bioblend/_tests/TestGalaxyHistories.py
bioblend/_tests/TestGalaxyInstance.py
bioblend/_tests/TestGalaxyInvocations.py
bioblend/_tests/TestGalaxyJobs.py
bioblend/_tests/TestGalaxyLibraries.py
bioblend/_tests/TestGalaxyObjects.py
bioblend/_tests/TestGalaxyQuotas.py
bioblend/_tests/TestGalaxyRoles.py
bioblend/_tests/TestGalaxyToolContainerResolution.py
bioblend/_tests/TestGalaxyToolData.py
bioblend/_tests/TestGalaxyToolDependencies.py
bioblend/_tests/TestGalaxyToolInputs.py
bioblend/_tests/TestGalaxyTools.py
bioblend/_tests/TestGalaxyUsers.py
bioblend/_tests/TestGalaxyWorkflows.py
bioblend/_tests/TestToolshed.py
bioblend/_tests/__init__.py
bioblend/_tests/pytest_galaxy_test_wrapper.py
bioblend/_tests/test_util.py
bioblend/_tests/data/1.bed
bioblend/_tests/data/Galaxy-History-Test-history-for-export.tar.gz
bioblend/_tests/data/paste_columns.ga
bioblend/_tests/data/paste_columns_collections.ga
bioblend/_tests/data/paste_columns_subworkflow.ga
bioblend/_tests/data/select_first.ga
bioblend/_tests/data/test_workflow_pause.ga
bioblend/_tests/data/workflow_with_parameter_input.ga
bioblend/galaxy/__init__.py
bioblend/galaxy/client.py
bioblend/galaxy/config/__init__.py
bioblend/galaxy/container_resolution/__init__.py
bioblend/galaxy/dataset_collections/__init__.py
bioblend/galaxy/datasets/__init__.py
bioblend/galaxy/datatypes/__init__.py
bioblend/galaxy/folders/__init__.py
bioblend/galaxy/forms/__init__.py
bioblend/galaxy/ftpfiles/__init__.py
bioblend/galaxy/genomes/__init__.py
bioblend/galaxy/groups/__init__.py
bioblend/galaxy/histories/__init__.py
bioblend/galaxy/invocations/__init__.py
bioblend/galaxy/jobs/__init__.py
bioblend/galaxy/libraries/__init__.py
bioblend-1.5.0.dist-info/CITATION
bioblend-1.5.0.dist-info/LICENSE
bioblend-1.5.0.dist-info/METADATA
bioblend-1.5.0.dist-info/WHEEL
bioblend-1.5.0.dist-info/entry_points.txt
bioblend-1.5.0.dist-info/top_level.txt
bioblend-1.5.0.dist-info/RECORD
