Metadata-Version: 2.2
Name: bioblend
Version: 1.5.0
Summary: Library for interacting with the Galaxy API
Home-page: https://bioblend.readthedocs.io/
Author: Enis Afgan
Author-email: afgane@gmail.com
Maintainer: Nicola Soranzo
Maintainer-email: nicola.soranzo@earlham.ac.uk
License: MIT
Project-URL: Bug Tracker, https://github.com/galaxyproject/bioblend/issues
Project-URL: Documentation, https://bioblend.readthedocs.io/
Project-URL: Source Code, https://github.com/galaxyproject/bioblend
Classifier: Development Status :: 5 - Production/Stable
Classifier: Intended Audience :: Developers
Classifier: License :: OSI Approved :: MIT License
Classifier: Operating System :: OS Independent
Classifier: Programming Language :: Python :: 3
Classifier: Programming Language :: Python :: 3.9
Classifier: Programming Language :: Python :: 3.10
Classifier: Programming Language :: Python :: 3.11
Classifier: Programming Language :: Python :: 3.12
Classifier: Programming Language :: Python :: 3.13
Classifier: Topic :: Scientific/Engineering :: Bio-Informatics
Classifier: Typing :: Typed
Requires-Python: >=3.9
License-File: CITATION
License-File: LICENSE
Requires-Dist: PyYAML
Requires-Dist: requests>=2.20.0
Requires-Dist: requests-toolbelt!=0.9.0,>=0.5.1
Requires-Dist: tuspy
Provides-Extra: testing
Requires-Dist: pytest; extra == "testing"
